find_work/plugins/gentoo_bugzilla/__init__.py
find_work/plugins/gentoo_bugzilla/cli.py
find_work/plugins/gentoo_bugzilla/constants.py
find_work/plugins/gentoo_bugzilla/internal.py
find_work/plugins/gentoo_bugzilla/options.py
find_work/plugins/gentoo_bugzilla/py.typed
find_work_bugzilla-1.0.0.dist-info/entry_points.txt
find_work_bugzilla-1.0.0.dist-info/WHEEL
find_work_bugzilla-1.0.0.dist-info/METADATA
find_work_bugzilla-1.0.0.dist-info/RECORD
