Metadata-Version: 2.3
Name: find-work-bugzilla
Version: 1.0.0
Summary: Personal advice utility for Gentoo package maintainers: Bugzilla plugin
Keywords: gentoo,ebuild,repository,maintainer,bugzilla
Author-email: Anna <cyber@sysrq.in>
Requires-Python: >=3.11
Classifier: Development Status :: 5 - Production/Stable
Classifier: Environment :: Console
Classifier: Framework :: Pydantic
Classifier: Framework :: Pydantic :: 2
Classifier: Intended Audience :: Developers
Classifier: License :: DFSG approved
Classifier: Operating System :: POSIX
Classifier: Programming Language :: Python
Classifier: Programming Language :: Python :: 3
Classifier: Programming Language :: Python :: 3 :: Only
Classifier: Topic :: System :: Software Distribution
Classifier: Topic :: Utilities
Classifier: Typing :: Typed
Requires-Dist: click
Requires-Dist: click-aliases
Requires-Dist: find-work[tabulate]<2,>=1
Requires-Dist: gentoopm<2
Requires-Dist: pydantic<3,>=2
Requires-Dist: pydantic-core<3,>=2
Requires-Dist: python-bugzilla
Requires-Dist: pytest ; extra == "test"
Requires-Dist: pytest-import-check ; extra == "test"
Project-URL: Changelog, https://git.sysrq.in/find-work-plugins/plain/find-work-bugzilla/ChangeLog
Project-URL: Home, https://find-work.sysrq.in/
Project-URL: Issues, https://bugs.sysrq.in/enter_bug.cgi?product=Software&component=find-work
Project-URL: Source, https://git.sysrq.in/find-work-plugins
Provides-Extra: test
